{"app":"2D Project","version":"1.0","scene":"AmbienteFase01","build":"","datehourstart":"2025-10-09 10:35:24","datehourend":"2025-10-09 10:35:29","reports":[{"id":"1","title":"[+LUDUS-monitor-start]","description":"O script iniciou em'H1', id: 54630","date":"2025-10-09 10:35:24"},{"id":"2","title":"[+LUDUS-mouse-move]:","description":"POS:(575;407;0)","date":"2025-10-09 10:35:25"},{"id":"3","title":"[+LUDUS-mouse-move]:","description":"POS:(579;403;0)","date":"2025-10-09 10:35:25"},{"id":"4","title":"[+LUDUS-mouse-move]:","description":"POS:(581;401;0)","date":"2025-10-09 10:35:25"},{"id":"5","title":"[+LUDUS-mouse-move]:","description":"POS:(581;400;0)","date":"2025-10-09 10:35:25"},{"id":"6","title":"[+LUDUS-mouse-move]:","description":"POS:(583;400;0)","date":"2025-10-09 10:35:25"},{"id":"7","title":"[+LUDUS-mouse-move]:","description":"POS:(584;400;0)","date":"2025-10-09 10:35:25"},{"id":"8","title":"[+LUDUS-mouse-move]:","description":"POS:(585;400;0)","date":"2025-10-09 10:35:25"},{"id":"9","title":"[+LUDUS-mouse-move]:","description":"POS:(588;401;0)","date":"2025-10-09 10:35:25"},{"id":"10","title":"[+LUDUS-mouse-move]:","description":"POS:(591;401;0)","date":"2025-10-09 10:35:25"},{"id":"11","title":"[+LUDUS-mouse-move]:","description":"POS:(592;403;0)","date":"2025-10-09 10:35:25"},{"id":"12","title":"[+LUDUS-mouse-move]:","description":"POS:(593;403;0)","date":"2025-10-09 10:35:25"},{"id":"13","title":"[+LUDUS-mouse-move]:","description":"POS:(595;404;0)","date":"2025-10-09 10:35:25"},{"id":"14","title":"[+LUDUS-mouse-move]:","description":"POS:(595;405;0)","date":"2025-10-09 10:35:25"},{"id":"15","title":"[+LUDUS-mouse-move]:","description":"POS:(595;406;0)","date":"2025-10-09 10:35:25"},{"id":"16","title":"[+LUDUS-mouse-move]:","description":"POS:(596;407;0)","date":"2025-10-09 10:35:25"},{"id":"17","title":"[+LUDUS-mouse-move]:","description":"POS:(597;408;0)","date":"2025-10-09 10:35:25"},{"id":"18","title":"[+LUDUS-mouse-move]:","description":"POS:(596;408;0)","date":"2025-10-09 10:35:25"},{"id":"19","title":"[+LUDUS-mouse-move]:","description":"POS:(593;406;0)","date":"2025-10-09 10:35:25"},{"id":"20","title":"[+LUDUS-mouse-move]:","description":"POS:(590;405;0)","date":"2025-10-09 10:35:25"},{"id":"21","title":"[+LUDUS-mouse-move]:","description":"POS:(585;404;0)","date":"2025-10-09 10:35:25"},{"id":"22","title":"[+LUDUS-drag]:","description":"objeto(Clone)(Clone) objeto_10 (UnityEngine.Sprite)","date":"2025-10-09 10:35:25"},{"id":"23","title":"[+LUDUS-drag]:","description":"objeto(Clone)(Clone) objeto_10 (UnityEngine.Sprite)","date":"2025-10-09 10:35:25"},{"id":"24","title":"[+LUDUS-mouse-move]:","description":"POS:(566;399;0)","date":"2025-10-09 10:35:25"},{"id":"25","title":"[+LUDUS-drag]:","description":"objeto(Clone)(Clone) objeto_10 (UnityEngine.Sprite)","date":"2025-10-09 10:35:25"},{"id":"26","title":"[+LUDUS-mouse-move]:","description":"POS:(561;399;0)","date":"2025-10-09 10:35:25"},{"id":"27","title":"[+LUDUS-drag]:","description":"objeto(Clone)(Clone) objeto_10 (UnityEngine.Sprite)","date":"2025-10-09 10:35:25"},{"id":"28","title":"[+LUDUS-mouse-move]:","description":"POS:(556;399;0)","date":"2025-10-09 10:35:25"},{"id":"29","title":"[+LUDUS-drag]:","description":"objeto(Clone)(Clone) objeto_10 (UnityEngine.Sprite)","date":"2025-10-09 10:35:25"},{"id":"30","title":"[+LUDUS-mouse-move]:","description":"POS:(547;399;0)","date":"2025-10-09 10:35:25"},{"id":"31","title":"[+LUDUS-drag]:","description":"objeto(Clone)(Clone) objeto_10 (UnityEngine.Sprite)","date":"2025-10-09 10:35:25"},{"id":"32","title":"[+LUDUS-mouse-move]:","description":"POS:(539;399;0)","date":"2025-10-09 10:35:25"},{"id":"33","title":"[+LUDUS-drag]:","description":"objeto(Clone)(Clone) objeto_10 (UnityEngine.Sprite)","date":"2025-10-09 10:35:25"},{"id":"34","title":"[+LUDUS-mouse-move]:","description":"POS:(531;399;0)","date":"2025-10-09 10:35:25"},{"id":"35","title":"[+LUDUS-drag]:","description":"objeto(Clone)(Clone) objeto_10 (UnityEngine.Sprite)","date":"2025-10-09 10:35:25"},{"id":"36","title":"[+LUDUS-mouse-move]:","description":"POS:(526;399;0)","date":"2025-10-09 10:35:25"},{"id":"37","title":"[+LUDUS-drag]:","description":"objeto(Clone)(Clone) objeto_10 (UnityEngine.Sprite)","date":"2025-10-09 10:35:25"},{"id":"38","title":"[+LUDUS-mouse-move]:","description":"POS:(518;399;0)","date":"2025-10-09 10:35:25"},{"id":"39","title":"[+LUDUS-drag]:","description":"objeto(Clone)(Clone) objeto_10 (UnityEngine.Sprite)","date":"2025-10-09 10:35:25"},{"id":"40","title":"[+LUDUS-mouse-move]:","description":"POS:(507;399;0)","date":"2025-10-09 10:35:25"},{"id":"41","title":"[+LUDUS-drag]:","description":"objeto(Clone)(Clone) objeto_10 (UnityEngine.Sprite)","date":"2025-10-09 10:35:25"},{"id":"42","title":"[+LUDUS-mouse-move]:","description":"POS:(494;399;0)","date":"2025-10-09 10:35:25"},{"id":"43","title":"[+LUDUS-drag]:","description":"objeto(Clone)(Clone) objeto_10 (UnityEngine.Sprite)","date":"2025-10-09 10:35:25"},{"id":"44","title":"[+LUDUS-mouse-move]:","description":"POS:(482;399;0)","date":"2025-10-09 10:35:25"},{"id":"45","title":"[+LUDUS-drag]:","description":"objeto(Clone)(Clone) objeto_10 (UnityEngine.Sprite)","date":"2025-10-09 10:35:25"},{"id":"46","title":"[+LUDUS-mouse-move]:","description":"POS:(470;399;0)","date":"2025-10-09 10:35:25"},{"id":"47","title":"[+LUDUS-drag]:","description":"objeto(Clone)(Clone) objeto_10 (UnityEngine.Sprite)","date":"2025-10-09 10:35:25"},{"id":"48","title":"[+LUDUS-mouse-move]:","description":"POS:(461;399;0)","date":"2025-10-09 10:35:25"},{"id":"49","title":"[+LUDUS-drag]:","description":"objeto(Clone)(Clone) objeto_10 (UnityEngine.Sprite)","date":"2025-10-09 10:35:25"},{"id":"50","title":"[+LUDUS-mouse-move]:","description":"POS:(454;399;0)","date":"2025-10-09 10:35:25"},{"id":"51","title":"[+LUDUS-drag]:","description":"objeto(Clone)(Clone) objeto_10 (UnityEngine.Sprite)","date":"2025-10-09 10:35:25"},{"id":"52","title":"[+LUDUS-mouse-move]:","description":"POS:(446;399;0)","date":"2025-10-09 10:35:25"},{"id":"53","title":"[+LUDUS-drag]:","description":"objeto(Clone)(Clone) objeto_10 (UnityEngine.Sprite)","date":"2025-10-09 10:35:25"},{"id":"54","title":"[+LUDUS-mouse-move]:","description":"POS:(443;399;0)","date":"2025-10-09 10:35:25"},{"id":"55","title":"[+LUDUS-drag]:","description":"objeto(Clone)(Clone) objeto_10 (UnityEngine.Sprite)","date":"2025-10-09 10:35:25"},{"id":"56","title":"[+LUDUS-mouse-move]:","description":"POS:(442;399;0)","date":"2025-10-09 10:35:25"},{"id":"57","title":"[+LUDUS-drag]:","description":"objeto(Clone)(Clone) objeto_10 (UnityEngine.Sprite)","date":"2025-10-09 10:35:25"},{"id":"58","title":"[+LUDUS-mouse-move]:","description":"POS:(439;399;0)","date":"2025-10-09 10:35:25"},{"id":"59","title":"[+LUDUS-drag]:","description":"objeto(Clone)(Clone) objeto_10 (UnityEngine.Sprite)","date":"2025-10-09 10:35:25"},{"id":"60","title":"[+LUDUS-mouse-move]:","description":"POS:(438;399;0)","date":"2025-10-09 10:35:25"},{"id":"61","title":"[+LUDUS-drag]:","description":"objeto(Clone)(Clone) objeto_10 (UnityEngine.Sprite)","date":"2025-10-09 10:35:25"},{"id":"62","title":"[+LUDUS-mouse-move]:","description":"POS:(436;399;0)","date":"2025-10-09 10:35:25"},{"id":"63","title":"[+LUDUS-drag]:","description":"objeto(Clone)(Clone) objeto_10 (UnityEngine.Sprite)","date":"2025-10-09 10:35:25"},{"id":"64","title":"[+LUDUS-mouse-move]:","description":"POS:(433;399;0)","date":"2025-10-09 10:35:25"},{"id":"65","title":"[+LUDUS-drag]:","description":"objeto(Clone)(Clone) objeto_10 (UnityEngine.Sprite)","date":"2025-10-09 10:35:25"},{"id":"66","title":"[+LUDUS-mouse-move]:","description":"POS:(430;399;0)","date":"2025-10-09 10:35:25"},{"id":"67","title":"[+LUDUS-drag]:","description":"objeto(Clone)(Clone) objeto_10 (UnityEngine.Sprite)","date":"2025-10-09 10:35:25"},{"id":"68","title":"[+LUDUS-mouse-move]:","description":"POS:(426;399;0)","date":"2025-10-09 10:35:25"},{"id":"69","title":"[+LUDUS-drag]:","description":"objeto(Clone)(Clone) objeto_10 (UnityEngine.Sprite)","date":"2025-10-09 10:35:25"},{"id":"70","title":"[+LUDUS-mouse-move]:","description":"POS:(422;399;0)","date":"2025-10-09 10:35:25"},{"id":"71","title":"[+LUDUS-drag]:","description":"objeto(Clone)(Clone) objeto_10 (UnityEngine.Sprite)","date":"2025-10-09 10:35:25"},{"id":"72","title":"[+LUDUS-mouse-move]:","description":"POS:(417;399;0)","date":"2025-10-09 10:35:25"},{"id":"73","title":"[+LUDUS-drag]:","description":"objeto(Clone)(Clone) objeto_10 (UnityEngine.Sprite)","date":"2025-10-09 10:35:25"},{"id":"74","title":"[+LUDUS-mouse-move]:","description":"POS:(412;400;0)","date":"2025-10-09 10:35:25"},{"id":"75","title":"[+LUDUS-drag]:","description":"objeto(Clone)(Clone) objeto_10 (UnityEngine.Sprite)","date":"2025-10-09 10:35:25"},{"id":"76","title":"[+LUDUS-mouse-move]:","description":"POS:(408;400;0)","date":"2025-10-09 10:35:25"},{"id":"77","title":"[+LUDUS-drag]:","description":"objeto(Clone)(Clone) objeto_10 (UnityEngine.Sprite)","date":"2025-10-09 10:35:25"},{"id":"78","title":"[+LUDUS-mouse-move]:","description":"POS:(405;402;0)","date":"2025-10-09 10:35:25"},{"id":"79","title":"[+LUDUS-drag]:","description":"objeto(Clone)(Clone) objeto_10 (UnityEngine.Sprite)","date":"2025-10-09 10:35:25"},{"id":"80","title":"[+LUDUS-mouse-move]:","description":"POS:(402;402;0)","date":"2025-10-09 10:35:25"},{"id":"81","title":"[+LUDUS-drag]:","description":"objeto(Clone)(Clone) objeto_10 (UnityEngine.Sprite)","date":"2025-10-09 10:35:25"},{"id":"82","title":"[+LUDUS-mouse-move]:","description":"POS:(399;402;0)","date":"2025-10-09 10:35:25"},{"id":"83","title":"[+LUDUS-drag]:","description":"objeto(Clone)(Clone) objeto_10 (UnityEngine.Sprite)","date":"2025-10-09 10:35:25"},{"id":"84","title":"[+LUDUS-mouse-move]:","description":"POS:(396;402;0)","date":"2025-10-09 10:35:25"},{"id":"85","title":"[+LUDUS-drag]:","description":"objeto(Clone)(Clone) objeto_10 (UnityEngine.Sprite)","date":"2025-10-09 10:35:25"},{"id":"86","title":"[+LUDUS-mouse-move]:","description":"POS:(393;402;0)","date":"2025-10-09 10:35:25"},{"id":"87","title":"[+LUDUS-drag]:","description":"objeto(Clone)(Clone) objeto_10 (UnityEngine.Sprite)","date":"2025-10-09 10:35:25"},{"id":"88","title":"[+LUDUS-mouse-move]:","description":"POS:(392;402;0)","date":"2025-10-09 10:35:25"},{"id":"89","title":"[+LUDUS-drag]:","description":"objeto(Clone)(Clone) objeto_10 (UnityEngine.Sprite)","date":"2025-10-09 10:35:25"},{"id":"90","title":"[+LUDUS-mouse-move]:","description":"POS:(390;402;0)","date":"2025-10-09 10:35:25"},{"id":"91","title":"[+LUDUS-drag]:","description":"objeto(Clone)(Clone) objeto_10 (UnityEngine.Sprite)","date":"2025-10-09 10:35:25"},{"id":"92","title":"[+LUDUS-mouse-move]:","description":"POS:(389;402;0)","date":"2025-10-09 10:35:25"},{"id":"93","title":"[+LUDUS-drag]:","description":"objeto(Clone)(Clone) objeto_10 (UnityEngine.Sprite)","date":"2025-10-09 10:35:25"},{"id":"94","title":"[+LUDUS-mouse-move]:","description":"POS:(388;402;0)","date":"2025-10-09 10:35:25"},{"id":"95","title":"[+LUDUS-drag]:","description":"objeto(Clone)(Clone) objeto_10 (UnityEngine.Sprite)","date":"2025-10-09 10:35:25"},{"id":"96","title":"[+LUDUS-mouse-move]:","description":"POS:(387;402;0)","date":"2025-10-09 10:35:25"},{"id":"97","title":"[+LUDUS-drag]:","description":"objeto(Clone)(Clone) objeto_10 (UnityEngine.Sprite)","date":"2025-10-09 10:35:25"},{"id":"98","title":"[+LUDUS-mouse-move]:","description":"POS:(385;402;0)","date":"2025-10-09 10:35:26"},{"id":"99","title":"[+LUDUS-drag]:","description":"objeto(Clone)(Clone) objeto_10 (UnityEngine.Sprite)","date":"2025-10-09 10:35:26"},{"id":"100","title":"[+LUDUS-mouse-move]:","description":"POS:(384;402;0)","date":"2025-10-09 10:35:26"},{"id":"101","title":"[+LUDUS-drag]:","description":"objeto(Clone)(Clone) objeto_10 (UnityEngine.Sprite)","date":"2025-10-09 10:35:26"},{"id":"102","title":"[+LUDUS-mouse-move]:","description":"POS:(383;402;0)","date":"2025-10-09 10:35:26"},{"id":"103","title":"[+LUDUS-drag]:","description":"objeto(Clone)(Clone) objeto_10 (UnityEngine.Sprite)","date":"2025-10-09 10:35:26"},{"id":"104","title":"[+LUDUS-mouse-move]:","description":"POS:(381;402;0)","date":"2025-10-09 10:35:26"},{"id":"105","title":"[+LUDUS-drag]:","description":"objeto(Clone)(Clone) objeto_10 (UnityEngine.Sprite)","date":"2025-10-09 10:35:26"},{"id":"106","title":"[+LUDUS-drop]:","description":"objeto(Clone)(Clone) objeto_10 (UnityEngine.Sprite)","date":"2025-10-09 10:35:26"},{"id":"107","title":"[+LUDUS-mouse-move]:","description":"POS:(383;402;0)","date":"2025-10-09 10:35:26"},{"id":"108","title":"[+LUDUS-mouse-move]:","description":"POS:(385;402;0)","date":"2025-10-09 10:35:26"},{"id":"109","title":"[+LUDUS-mouse-move]:","description":"POS:(388;402;0)","date":"2025-10-09 10:35:26"},{"id":"110","title":"[+LUDUS-mouse-move]:","description":"POS:(392;402;0)","date":"2025-10-09 10:35:26"},{"id":"111","title":"[+LUDUS-mouse-move]:","description":"POS:(396;402;0)","date":"2025-10-09 10:35:26"},{"id":"112","title":"[+LUDUS-mouse-move]:","description":"POS:(401;402;0)","date":"2025-10-09 10:35:26"},{"id":"113","title":"[+LUDUS-mouse-move]:","description":"POS:(404;402;0)","date":"2025-10-09 10:35:26"},{"id":"114","title":"[+LUDUS-mouse-move]:","description":"POS:(409;402;0)","date":"2025-10-09 10:35:26"},{"id":"115","title":"[+LUDUS-mouse-move]:","description":"POS:(415;402;0)","date":"2025-10-09 10:35:26"},{"id":"116","title":"[+LUDUS-mouse-move]:","description":"POS:(426;404;0)","date":"2025-10-09 10:35:26"},{"id":"117","title":"[+LUDUS-mouse-move]:","description":"POS:(432;406;0)","date":"2025-10-09 10:35:26"},{"id":"118","title":"[+LUDUS-mouse-move]:","description":"POS:(439;408;0)","date":"2025-10-09 10:35:26"},{"id":"119","title":"[+LUDUS-mouse-move]:","description":"POS:(446;410;0)","date":"2025-10-09 10:35:26"},{"id":"120","title":"[+LUDUS-mouse-move]:","description":"POS:(454;412;0)","date":"2025-10-09 10:35:26"},{"id":"121","title":"[+LUDUS-mouse-move]:","description":"POS:(460;414;0)","date":"2025-10-09 10:35:26"},{"id":"122","title":"[+LUDUS-mouse-move]:","description":"POS:(468;416;0)","date":"2025-10-09 10:35:26"},{"id":"123","title":"[+LUDUS-mouse-move]:","description":"POS:(476;418;0)","date":"2025-10-09 10:35:26"},{"id":"124","title":"[+LUDUS-mouse-move]:","description":"POS:(483;421;0)","date":"2025-10-09 10:35:26"},{"id":"125","title":"[+LUDUS-mouse-move]:","description":"POS:(489;423;0)","date":"2025-10-09 10:35:26"},{"id":"126","title":"[+LUDUS-mouse-move]:","description":"POS:(494;426;0)","date":"2025-10-09 10:35:26"},{"id":"127","title":"[+LUDUS-mouse-move]:","description":"POS:(497;427;0)","date":"2025-10-09 10:35:26"},{"id":"128","title":"[+LUDUS-mouse-move]:","description":"POS:(502;429;0)","date":"2025-10-09 10:35:26"},{"id":"129","title":"[+LUDUS-mouse-move]:","description":"POS:(506;431;0)","date":"2025-10-09 10:35:26"},{"id":"130","title":"[+LUDUS-mouse-move]:","description":"POS:(510;433;0)","date":"2025-10-09 10:35:26"},{"id":"131","title":"[+LUDUS-mouse-move]:","description":"POS:(513;434;0)","date":"2025-10-09 10:35:26"},{"id":"132","title":"[+LUDUS-mouse-move]:","description":"POS:(516;434;0)","date":"2025-10-09 10:35:26"},{"id":"133","title":"[+LUDUS-mouse-move]:","description":"POS:(517;436;0)","date":"2025-10-09 10:35:26"},{"id":"134","title":"[+LUDUS-mouse-move]:","description":"POS:(520;437;0)","date":"2025-10-09 10:35:26"},{"id":"135","title":"[+LUDUS-mouse-move]:","description":"POS:(522;437;0)","date":"2025-10-09 10:35:26"},{"id":"136","title":"[+LUDUS-mouse-move]:","description":"POS:(523;437;0)","date":"2025-10-09 10:35:26"},{"id":"137","title":"[+LUDUS-mouse-move]:","description":"POS:(524;437;0)","date":"2025-10-09 10:35:26"},{"id":"138","title":"[+LUDUS-mouse-move]:","description":"POS:(527;437;0)","date":"2025-10-09 10:35:26"},{"id":"139","title":"[+LUDUS-mouse-move]:","description":"POS:(529;434;0)","date":"2025-10-09 10:35:26"},{"id":"140","title":"[+LUDUS-mouse-move]:","description":"POS:(529;423;0)","date":"2025-10-09 10:35:26"},{"id":"141","title":"[+LUDUS-drag]:","description":"objeto(Clone)(Clone) objeto_10 (UnityEngine.Sprite)","date":"2025-10-09 10:35:26"},{"id":"142","title":"[+LUDUS-mouse-move]:","description":"POS:(532;406;0)","date":"2025-10-09 10:35:26"},{"id":"143","title":"[+LUDUS-drag]:","description":"objeto(Clone)(Clone) objeto_10 (UnityEngine.Sprite)","date":"2025-10-09 10:35:26"},{"id":"144","title":"[+LUDUS-mouse-move]:","description":"POS:(535;383;0)","date":"2025-10-09 10:35:26"},{"id":"145","title":"[+LUDUS-drag]:","description":"objeto(Clone)(Clone) objeto_10 (UnityEngine.Sprite)","date":"2025-10-09 10:35:26"},{"id":"146","title":"[+LUDUS-drag]:","description":"objeto(Clone)(Clone) objeto_10 (UnityEngine.Sprite)","date":"2025-10-09 10:35:26"},{"id":"147","title":"[+LUDUS-mouse-move]:","description":"POS:(538;317;0)","date":"2025-10-09 10:35:26"},{"id":"148","title":"[+LUDUS-drag]:","description":"objeto(Clone)(Clone) objeto_10 (UnityEngine.Sprite)","date":"2025-10-09 10:35:26"},{"id":"149","title":"[+LUDUS-mouse-move]:","description":"POS:(538;276;0)","date":"2025-10-09 10:35:26"},{"id":"150","title":"[+LUDUS-drag]:","description":"objeto(Clone)(Clone) objeto_10 (UnityEngine.Sprite)","date":"2025-10-09 10:35:26"},{"id":"151","title":"[+LUDUS-mouse-move]:","description":"POS:(541;237;0)","date":"2025-10-09 10:35:26"},{"id":"152","title":"[+LUDUS-drag]:","description":"objeto(Clone)(Clone) objeto_10 (UnityEngine.Sprite)","date":"2025-10-09 10:35:26"},{"id":"153","title":"[+LUDUS-drag]:","description":"objeto(Clone)(Clone) objeto_10 (UnityEngine.Sprite)","date":"2025-10-09 10:35:26"},{"id":"154","title":"[+LUDUS-mouse-move]:","description":"POS:(541;172;0)","date":"2025-10-09 10:35:26"},{"id":"155","title":"[+LUDUS-drag]:","description":"objeto(Clone)(Clone) objeto_10 (UnityEngine.Sprite)","date":"2025-10-09 10:35:26"},{"id":"156","title":"[+LUDUS-mouse-move]:","description":"POS:(541;147;0)","date":"2025-10-09 10:35:26"},{"id":"157","title":"[+LUDUS-drag]:","description":"objeto(Clone)(Clone) objeto_10 (UnityEngine.Sprite)","date":"2025-10-09 10:35:26"},{"id":"158","title":"[+LUDUS-mouse-move]:","description":"POS:(541;128;0)","date":"2025-10-09 10:35:26"},{"id":"159","title":"[+LUDUS-drag]:","description":"objeto(Clone)(Clone) objeto_10 (UnityEngine.Sprite)","date":"2025-10-09 10:35:26"},{"id":"160","title":"[+LUDUS-mouse-move]:","description":"POS:(541;109;0)","date":"2025-10-09 10:35:26"},{"id":"161","title":"[+LUDUS-drag]:","description":"objeto(Clone)(Clone) objeto_10 (UnityEngine.Sprite)","date":"2025-10-09 10:35:26"},{"id":"162","title":"[+LUDUS-mouse-move]:","description":"POS:(541;96;0)","date":"2025-10-09 10:35:26"},{"id":"163","title":"[+LUDUS-drag]:","description":"objeto(Clone)(Clone) objeto_10 (UnityEngine.Sprite)","date":"2025-10-09 10:35:26"},{"id":"164","title":"[+LUDUS-drag]:","description":"objeto(Clone)(Clone) objeto_10 (UnityEngine.Sprite)","date":"2025-10-09 10:35:26"},{"id":"165","title":"[+LUDUS-drag]:","description":"objeto(Clone)(Clone) objeto_10 (UnityEngine.Sprite)","date":"2025-10-09 10:35:26"},{"id":"166","title":"[+LUDUS-mouse-move]:","description":"POS:(551;57;0)","date":"2025-10-09 10:35:26"},{"id":"167","title":"[+LUDUS-drag]:","description":"objeto(Clone)(Clone) objeto_10 (UnityEngine.Sprite)","date":"2025-10-09 10:35:26"},{"id":"168","title":"[+LUDUS-mouse-move]:","description":"POS:(553;49;0)","date":"2025-10-09 10:35:26"},{"id":"169","title":"[+LUDUS-drag]:","description":"objeto(Clone)(Clone) objeto_10 (UnityEngine.Sprite)","date":"2025-10-09 10:35:26"},{"id":"170","title":"[+LUDUS-drag]:","description":"objeto(Clone)(Clone) objeto_10 (UnityEngine.Sprite)","date":"2025-10-09 10:35:26"},{"id":"171","title":"[+LUDUS-mouse-move]:","description":"POS:(555;41;0)","date":"2025-10-09 10:35:26"},{"id":"172","title":"[+LUDUS-drag]:","description":"objeto(Clone)(Clone) objeto_10 (UnityEngine.Sprite)","date":"2025-10-09 10:35:26"},{"id":"173","title":"[+LUDUS-mouse-move]:","description":"POS:(556;39;0)","date":"2025-10-09 10:35:26"},{"id":"174","title":"[+LUDUS-drag]:","description":"objeto(Clone)(Clone) objeto_10 (UnityEngine.Sprite)","date":"2025-10-09 10:35:26"},{"id":"175","title":"[+LUDUS-mouse-move]:","description":"POS:(557;38;0)","date":"2025-10-09 10:35:26"},{"id":"176","title":"[+LUDUS-drag]:","description":"objeto(Clone)(Clone) objeto_10 (UnityEngine.Sprite)","date":"2025-10-09 10:35:26"},{"id":"177","title":"[+LUDUS-mouse-move]:","description":"POS:(557;39;0)","date":"2025-10-09 10:35:26"},{"id":"178","title":"[+LUDUS-drag]:","description":"objeto(Clone)(Clone) objeto_10 (UnityEngine.Sprite)","date":"2025-10-09 10:35:26"},{"id":"179","title":"[+LUDUS-mouse-move]:","description":"POS:(557;42;0)","date":"2025-10-09 10:35:26"},{"id":"180","title":"[+LUDUS-drag]:","description":"objeto(Clone)(Clone) objeto_10 (UnityEngine.Sprite)","date":"2025-10-09 10:35:26"},{"id":"181","title":"[+LUDUS-mouse-move]:","description":"POS:(557;46;0)","date":"2025-10-09 10:35:26"},{"id":"182","title":"[+LUDUS-drag]:","description":"objeto(Clone)(Clone) objeto_10 (UnityEngine.Sprite)","date":"2025-10-09 10:35:26"},{"id":"183","title":"[+LUDUS-drag]:","description":"objeto(Clone)(Clone) objeto_10 (UnityEngine.Sprite)","date":"2025-10-09 10:35:26"},{"id":"184","title":"[+LUDUS-mouse-move]:","description":"POS:(556;61;0)","date":"2025-10-09 10:35:26"},{"id":"185","title":"[+LUDUS-drag]:","description":"objeto(Clone)(Clone) objeto_10 (UnityEngine.Sprite)","date":"2025-10-09 10:35:26"},{"id":"186","title":"[+LUDUS-mouse-move]:","description":"POS:(556;69;0)","date":"2025-10-09 10:35:26"},{"id":"187","title":"[+LUDUS-drag]:","description":"objeto(Clone)(Clone) objeto_10 (UnityEngine.Sprite)","date":"2025-10-09 10:35:26"},{"id":"188","title":"[+LUDUS-drag]:","description":"objeto(Clone)(Clone) objeto_10 (UnityEngine.Sprite)","date":"2025-10-09 10:35:26"},{"id":"189","title":"[+LUDUS-drag]:","description":"objeto(Clone)(Clone) objeto_10 (UnityEngine.Sprite)","date":"2025-10-09 10:35:26"},{"id":"190","title":"[+LUDUS-mouse-move]:","description":"POS:(554;106;0)","date":"2025-10-09 10:35:26"},{"id":"191","title":"[+LUDUS-drag]:","description":"objeto(Clone)(Clone) objeto_10 (UnityEngine.Sprite)","date":"2025-10-09 10:35:26"},{"id":"192","title":"[+LUDUS-mouse-move]:","description":"POS:(554;114;0)","date":"2025-10-09 10:35:26"},{"id":"193","title":"[+LUDUS-drag]:","description":"objeto(Clone)(Clone) objeto_10 (UnityEngine.Sprite)","date":"2025-10-09 10:35:26"},{"id":"194","title":"[+LUDUS-mouse-move]:","description":"POS:(552;123;0)","date":"2025-10-09 10:35:26"},{"id":"195","title":"[+LUDUS-drag]:","description":"objeto(Clone)(Clone) objeto_10 (UnityEngine.Sprite)","date":"2025-10-09 10:35:26"},{"id":"196","title":"[+LUDUS-mouse-move]:","description":"POS:(552;128;0)","date":"2025-10-09 10:35:26"},{"id":"197","title":"[+LUDUS-drag]:","description":"objeto(Clone)(Clone) objeto_10 (UnityEngine.Sprite)","date":"2025-10-09 10:35:26"},{"id":"198","title":"[+LUDUS-mouse-move]:","description":"POS:(550;134;0)","date":"2025-10-09 10:35:26"},{"id":"199","title":"[+LUDUS-drag]:","description":"objeto(Clone)(Clone) objeto_10 (UnityEngine.Sprite)","date":"2025-10-09 10:35:26"},{"id":"200","title":"[+LUDUS-mouse-move]:","description":"POS:(550;137;0)","date":"2025-10-09 10:35:26"},{"id":"201","title":"[+LUDUS-drag]:","description":"objeto(Clone)(Clone) objeto_10 (UnityEngine.Sprite)","date":"2025-10-09 10:35:26"},{"id":"202","title":"[+LUDUS-mouse-move]:","description":"POS:(549;139;0)","date":"2025-10-09 10:35:26"},{"id":"203","title":"[+LUDUS-drag]:","description":"objeto(Clone)(Clone) objeto_10 (UnityEngine.Sprite)","date":"2025-10-09 10:35:26"},{"id":"204","title":"[+LUDUS-mouse-move]:","description":"POS:(549;140;0)","date":"2025-10-09 10:35:26"},{"id":"205","title":"[+LUDUS-drag]:","description":"objeto(Clone)(Clone) objeto_10 (UnityEngine.Sprite)","date":"2025-10-09 10:35:26"},{"id":"206","title":"[+LUDUS-mouse-move]:","description":"POS:(549;141;0)","date":"2025-10-09 10:35:26"},{"id":"207","title":"[+LUDUS-drag]:","description":"objeto(Clone)(Clone) objeto_10 (UnityEngine.Sprite)","date":"2025-10-09 10:35:26"},{"id":"208","title":"[+LUDUS-mouse-move]:","description":"POS:(549;142;0)","date":"2025-10-09 10:35:26"},{"id":"209","title":"[+LUDUS-drag]:","description":"objeto(Clone)(Clone) objeto_10 (UnityEngine.Sprite)","date":"2025-10-09 10:35:26"},{"id":"210","title":"[+LUDUS-drop]:","description":"objeto(Clone)(Clone) objeto_10 (UnityEngine.Sprite)","date":"2025-10-09 10:35:26"},{"id":"211","title":"[+LUDUS-mouse-move]:","description":"POS:(549;144;0)","date":"2025-10-09 10:35:27"},{"id":"212","title":"[+LUDUS-mouse-move]:","description":"POS:(550;144;0)","date":"2025-10-09 10:35:27"},{"id":"213","title":"[+LUDUS-mouse-move]:","description":"POS:(550;145;0)","date":"2025-10-09 10:35:27"},{"id":"214","title":"[+LUDUS-mouse-move]:","description":"POS:(550;146;0)","date":"2025-10-09 10:35:27"},{"id":"215","title":"[+LUDUS-mouse-move]:","description":"POS:(551;146;0)","date":"2025-10-09 10:35:27"},{"id":"216","title":"[+LUDUS-mouse-move]:","description":"POS:(552;148;0)","date":"2025-10-09 10:35:27"},{"id":"217","title":"[+LUDUS-mouse-move]:","description":"POS:(553;148;0)","date":"2025-10-09 10:35:27"},{"id":"218","title":"[+LUDUS-mouse-move]:","description":"POS:(556;151;0)","date":"2025-10-09 10:35:27"},{"id":"219","title":"[+LUDUS-mouse-move]:","description":"POS:(557;155;0)","date":"2025-10-09 10:35:27"},{"id":"220","title":"[+LUDUS-mouse-move]:","description":"POS:(559;158;0)","date":"2025-10-09 10:35:27"},{"id":"221","title":"[+LUDUS-mouse-move]:","description":"POS:(563;164;0)","date":"2025-10-09 10:35:27"},{"id":"222","title":"[+LUDUS-mouse-move]:","description":"POS:(565;170;0)","date":"2025-10-09 10:35:27"},{"id":"223","title":"[+LUDUS-mouse-move]:","description":"POS:(567;176;0)","date":"2025-10-09 10:35:27"},{"id":"224","title":"[+LUDUS-mouse-move]:","description":"POS:(569;187;0)","date":"2025-10-09 10:35:27"},{"id":"225","title":"[+LUDUS-mouse-move]:","description":"POS:(579;197;0)","date":"2025-10-09 10:35:27"},{"id":"226","title":"[+LUDUS-mouse-move]:","description":"POS:(600;212;0)","date":"2025-10-09 10:35:27"},{"id":"227","title":"[+LUDUS-mouse-move]:","description":"POS:(638;249;0)","date":"2025-10-09 10:35:27"},{"id":"228","title":"[+LUDUS-mouse-move]:","description":"POS:(655;272;0)","date":"2025-10-09 10:35:27"},{"id":"229","title":"[+LUDUS-mouse-move]:","description":"POS:(667;286;0)","date":"2025-10-09 10:35:27"},{"id":"230","title":"[+LUDUS-mouse-move]:","description":"POS:(672;299;0)","date":"2025-10-09 10:35:27"},{"id":"231","title":"[+LUDUS-mouse-move]:","description":"POS:(674;304;0)","date":"2025-10-09 10:35:27"},{"id":"232","title":"[+LUDUS-mouse-move]:","description":"POS:(676;313;0)","date":"2025-10-09 10:35:27"},{"id":"233","title":"[+LUDUS-mouse-move]:","description":"POS:(678;318;0)","date":"2025-10-09 10:35:27"},{"id":"234","title":"[+LUDUS-mouse-move]:","description":"POS:(678;321;0)","date":"2025-10-09 10:35:27"},{"id":"235","title":"[+LUDUS-mouse-move]:","description":"POS:(678;323;0)","date":"2025-10-09 10:35:27"},{"id":"236","title":"[+LUDUS-mouse-move]:","description":"POS:(677;324;0)","date":"2025-10-09 10:35:27"},{"id":"237","title":"[+LUDUS-mouse-move]:","description":"POS:(676;324;0)","date":"2025-10-09 10:35:27"},{"id":"238","title":"[+LUDUS-mouse-move]:","description":"POS:(672;313;0)","date":"2025-10-09 10:35:27"},{"id":"239","title":"[+LUDUS-mouse-move]:","description":"POS:(663;290;0)","date":"2025-10-09 10:35:27"},{"id":"240","title":"[+LUDUS-mouse-move]:","description":"POS:(653;263;0)","date":"2025-10-09 10:35:27"},{"id":"241","title":"[+LUDUS-mouse-move]:","description":"POS:(637;229;0)","date":"2025-10-09 10:35:27"},{"id":"242","title":"[+LUDUS-mouse-move]:","description":"POS:(584;133;0)","date":"2025-10-09 10:35:27"},{"id":"243","title":"[+LUDUS-mouse-move]:","description":"POS:(575;117;0)","date":"2025-10-09 10:35:27"},{"id":"244","title":"[+LUDUS-mouse-move]:","description":"POS:(565;101;0)","date":"2025-10-09 10:35:27"},{"id":"245","title":"[+LUDUS-mouse-move]:","description":"POS:(558;86;0)","date":"2025-10-09 10:35:27"},{"id":"246","title":"[+LUDUS-mouse-move]:","description":"POS:(547;61;0)","date":"2025-10-09 10:35:27"},{"id":"247","title":"[+LUDUS-mouse-move]:","description":"POS:(547;59;0)","date":"2025-10-09 10:35:27"},{"id":"248","title":"[+LUDUS-mouse-move]:","description":"POS:(547;57;0)","date":"2025-10-09 10:35:27"},{"id":"249","title":"[+LUDUS-mouse-move]:","description":"POS:(547;56;0)","date":"2025-10-09 10:35:27"},{"id":"250","title":"[+LUDUS-mouse-move]:","description":"POS:(547;55;0)","date":"2025-10-09 10:35:27"},{"id":"251","title":"[+LUDUS-mouse-move]:","description":"POS:(544;55;0)","date":"2025-10-09 10:35:27"},{"id":"252","title":"[+LUDUS-mouse-move]:","description":"POS:(539;55;0)","date":"2025-10-09 10:35:27"},{"id":"253","title":"[+LUDUS-mouse-move]:","description":"POS:(528;59;0)","date":"2025-10-09 10:35:27"},{"id":"254","title":"[+LUDUS-mouse-move]:","description":"POS:(513;66;0)","date":"2025-10-09 10:35:27"},{"id":"255","title":"[+LUDUS-mouse-move]:","description":"POS:(487;72;0)","date":"2025-10-09 10:35:27"},{"id":"256","title":"[+LUDUS-mouse-move]:","description":"POS:(424;89;0)","date":"2025-10-09 10:35:27"},{"id":"257","title":"[+LUDUS-mouse-move]:","description":"POS:(397;99;0)","date":"2025-10-09 10:35:27"},{"id":"258","title":"[+LUDUS-mouse-move]:","description":"POS:(361;112;0)","date":"2025-10-09 10:35:27"},{"id":"259","title":"[+LUDUS-mouse-move]:","description":"POS:(333;123;0)","date":"2025-10-09 10:35:27"},{"id":"260","title":"[+LUDUS-mouse-move]:","description":"POS:(305;133;0)","date":"2025-10-09 10:35:27"},{"id":"261","title":"[+LUDUS-mouse-move]:","description":"POS:(285;140;0)","date":"2025-10-09 10:35:27"},{"id":"262","title":"[+LUDUS-mouse-move]:","description":"POS:(273;146;0)","date":"2025-10-09 10:35:27"},{"id":"263","title":"[+LUDUS-mouse-move]:","description":"POS:(265;148;0)","date":"2025-10-09 10:35:27"},{"id":"264","title":"[+LUDUS-mouse-move]:","description":"POS:(259;150;0)","date":"2025-10-09 10:35:27"},{"id":"265","title":"[+LUDUS-mouse-move]:","description":"POS:(258;149;0)","date":"2025-10-09 10:35:27"},{"id":"266","title":"[+LUDUS-mouse-move]:","description":"POS:(260;146;0)","date":"2025-10-09 10:35:27"},{"id":"267","title":"[+LUDUS-mouse-move]:","description":"POS:(263;146;0)","date":"2025-10-09 10:35:27"},{"id":"268","title":"[+LUDUS-mouse-move]:","description":"POS:(270;146;0)","date":"2025-10-09 10:35:27"},{"id":"269","title":"[+LUDUS-drag]:","description":"PainelSombra Frame 2 (4) (UnityEngine.Sprite)","date":"2025-10-09 10:35:27"},{"id":"270","title":"[+LUDUS-mouse-move]:","description":"POS:(275;146;0)","date":"2025-10-09 10:35:27"},{"id":"271","title":"[+LUDUS-drag]:","description":"PainelSombra Frame 2 (4) (UnityEngine.Sprite)","date":"2025-10-09 10:35:27"},{"id":"272","title":"[+LUDUS-mouse-move]:","description":"POS:(283;146;0)","date":"2025-10-09 10:35:27"},{"id":"273","title":"[+LUDUS-drag]:","description":"PainelSombra Frame 2 (4) (UnityEngine.Sprite)","date":"2025-10-09 10:35:27"},{"id":"274","title":"[+LUDUS-mouse-move]:","description":"POS:(296;146;0)","date":"2025-10-09 10:35:27"},{"id":"275","title":"[+LUDUS-drag]:","description":"PainelSombra Frame 2 (4) (UnityEngine.Sprite)","date":"2025-10-09 10:35:27"},{"id":"276","title":"[+LUDUS-mouse-move]:","description":"POS:(317;146;0)","date":"2025-10-09 10:35:27"},{"id":"277","title":"[+LUDUS-drag]:","description":"PainelSombra Frame 2 (4) (UnityEngine.Sprite)","date":"2025-10-09 10:35:27"},{"id":"278","title":"[+LUDUS-mouse-click]:","description":"Botão esquerdo .PainelSombra","date":"2025-10-09 10:35:27"},{"id":"279","title":"[+LUDUS-drop]:","description":"PainelSombra Frame 2 (4) (UnityEngine.Sprite)","date":"2025-10-09 10:35:27"},{"id":"280","title":"[+LUDUS-mouse-move]:","description":"POS:(342;143;0)","date":"2025-10-09 10:35:27"},{"id":"281","title":"[+LUDUS-mouse-move]:","description":"POS:(384;140;0)","date":"2025-10-09 10:35:27"},{"id":"282","title":"[+LUDUS-mouse-move]:","description":"POS:(427;140;0)","date":"2025-10-09 10:35:27"},{"id":"283","title":"[+LUDUS-mouse-move]:","description":"POS:(476;140;0)","date":"2025-10-09 10:35:27"},{"id":"284","title":"[+LUDUS-mouse-move]:","description":"POS:(527;140;0)","date":"2025-10-09 10:35:27"},{"id":"285","title":"[+LUDUS-mouse-move]:","description":"POS:(614;140;0)","date":"2025-10-09 10:35:27"},{"id":"286","title":"[+LUDUS-mouse-move]:","description":"POS:(661;140;0)","date":"2025-10-09 10:35:27"},{"id":"287","title":"[+LUDUS-mouse-move]:","description":"POS:(671;140;0)","date":"2025-10-09 10:35:27"},{"id":"288","title":"[+LUDUS-mouse-move]:","description":"POS:(676;141;0)","date":"2025-10-09 10:35:27"},{"id":"289","title":"[+LUDUS-mouse-move]:","description":"POS:(679;141;0)","date":"2025-10-09 10:35:27"},{"id":"290","title":"[+LUDUS-mouse-move]:","description":"POS:(679;142;0)","date":"2025-10-09 10:35:27"},{"id":"291","title":"[+LUDUS-mouse-move]:","description":"POS:(681;142;0)","date":"2025-10-09 10:35:27"},{"id":"292","title":"[+LUDUS-mouse-move]:","description":"POS:(684;142;0)","date":"2025-10-09 10:35:27"},{"id":"293","title":"[+LUDUS-mouse-move]:","description":"POS:(685;142;0)","date":"2025-10-09 10:35:27"},{"id":"294","title":"[+LUDUS-mouse-move]:","description":"POS:(688;142;0)","date":"2025-10-09 10:35:27"},{"id":"295","title":"[+LUDUS-mouse-move]:","description":"POS:(693;142;0)","date":"2025-10-09 10:35:27"},{"id":"296","title":"[+LUDUS-drag]:","description":"PainelSombra Frame 2 (4) (UnityEngine.Sprite)","date":"2025-10-09 10:35:27"},{"id":"297","title":"[+LUDUS-mouse-move]:","description":"POS:(696;142;0)","date":"2025-10-09 10:35:27"},{"id":"298","title":"[+LUDUS-drag]:","description":"PainelSombra Frame 2 (4) (UnityEngine.Sprite)","date":"2025-10-09 10:35:27"},{"id":"299","title":"[+LUDUS-mouse-move]:","description":"POS:(699;142;0)","date":"2025-10-09 10:35:27"},{"id":"300","title":"[+LUDUS-drag]:","description":"PainelSombra Frame 2 (4) (UnityEngine.Sprite)","date":"2025-10-09 10:35:27"},{"id":"301","title":"[+LUDUS-mouse-click]:","description":"Botão esquerdo .PainelSombra","date":"2025-10-09 10:35:27"},{"id":"302","title":"[+LUDUS-drop]:","description":"PainelSombra Frame 2 (4) (UnityEngine.Sprite)","date":"2025-10-09 10:35:27"},{"id":"303","title":"[+LUDUS-mouse-move]:","description":"POS:(706;142;0)","date":"2025-10-09 10:35:27"},{"id":"304","title":"[+LUDUS-mouse-move]:","description":"POS:(712;141;0)","date":"2025-10-09 10:35:27"},{"id":"305","title":"[+LUDUS-mouse-move]:","description":"POS:(718;139;0)","date":"2025-10-09 10:35:27"},{"id":"306","title":"[+LUDUS-mouse-move]:","description":"POS:(721;139;0)","date":"2025-10-09 10:35:28"},{"id":"307","title":"[+LUDUS-mouse-move]:","description":"POS:(726;139;0)","date":"2025-10-09 10:35:28"},{"id":"308","title":"[+LUDUS-mouse-move]:","description":"POS:(729;138;0)","date":"2025-10-09 10:35:28"},{"id":"309","title":"[+LUDUS-mouse-move]:","description":"POS:(733;138;0)","date":"2025-10-09 10:35:28"},{"id":"310","title":"[+LUDUS-mouse-move]:","description":"POS:(737;138;0)","date":"2025-10-09 10:35:28"},{"id":"311","title":"[+LUDUS-mouse-move]:","description":"POS:(744;138;0)","date":"2025-10-09 10:35:28"},{"id":"312","title":"[+LUDUS-mouse-move]:","description":"POS:(748;138;0)","date":"2025-10-09 10:35:28"},{"id":"313","title":"[+LUDUS-mouse-move]:","description":"POS:(754;138;0)","date":"2025-10-09 10:35:28"},{"id":"314","title":"[+LUDUS-mouse-move]:","description":"POS:(758;138;0)","date":"2025-10-09 10:35:28"},{"id":"315","title":"[+LUDUS-mouse-move]:","description":"POS:(762;138;0)","date":"2025-10-09 10:35:28"},{"id":"316","title":"[+LUDUS-mouse-move]:","description":"POS:(765;138;0)","date":"2025-10-09 10:35:28"},{"id":"317","title":"[+LUDUS-mouse-move]:","description":"POS:(775;138;0)","date":"2025-10-09 10:35:28"},{"id":"318","title":"[+LUDUS-mouse-move]:","description":"POS:(778;138;0)","date":"2025-10-09 10:35:28"},{"id":"319","title":"[+LUDUS-mouse-move]:","description":"POS:(781;138;0)","date":"2025-10-09 10:35:28"},{"id":"320","title":"[+LUDUS-drag]:","description":"PainelSombra Frame 2 (4) (UnityEngine.Sprite)","date":"2025-10-09 10:35:28"},{"id":"321","title":"[+LUDUS-mouse-move]:","description":"POS:(786;138;0)","date":"2025-10-09 10:35:28"},{"id":"322","title":"[+LUDUS-drag]:","description":"PainelSombra Frame 2 (4) (UnityEngine.Sprite)","date":"2025-10-09 10:35:28"},{"id":"323","title":"[+LUDUS-mouse-move]:","description":"POS:(792;138;0)","date":"2025-10-09 10:35:28"},{"id":"324","title":"[+LUDUS-drag]:","description":"PainelSombra Frame 2 (4) (UnityEngine.Sprite)","date":"2025-10-09 10:35:28"},{"id":"325","title":"[+LUDUS-mouse-move]:","description":"POS:(800;135;0)","date":"2025-10-09 10:35:28"},{"id":"326","title":"[+LUDUS-drag]:","description":"PainelSombra Frame 2 (4) (UnityEngine.Sprite)","date":"2025-10-09 10:35:28"},{"id":"327","title":"[+LUDUS-mouse-move]:","description":"POS:(811;133;0)","date":"2025-10-09 10:35:28"},{"id":"328","title":"[+LUDUS-drag]:","description":"PainelSombra Frame 2 (4) (UnityEngine.Sprite)","date":"2025-10-09 10:35:28"},{"id":"329","title":"[+LUDUS-mouse-move]:","description":"POS:(822;133;0)","date":"2025-10-09 10:35:28"},{"id":"330","title":"[+LUDUS-drag]:","description":"PainelSombra Frame 2 (4) (UnityEngine.Sprite)","date":"2025-10-09 10:35:28"},{"id":"331","title":"[+LUDUS-mouse-move]:","description":"POS:(832;131;0)","date":"2025-10-09 10:35:28"},{"id":"332","title":"[+LUDUS-drag]:","description":"PainelSombra Frame 2 (4) (UnityEngine.Sprite)","date":"2025-10-09 10:35:28"},{"id":"333","title":"[+LUDUS-mouse-click]:","description":"Botão esquerdo .PainelSombra","date":"2025-10-09 10:35:28"},{"id":"334","title":"[+LUDUS-drop]:","description":"PainelSombra Frame 2 (4) (UnityEngine.Sprite)","date":"2025-10-09 10:35:28"},{"id":"335","title":"[+LUDUS-mouse-move]:","description":"POS:(843;129;0)","date":"2025-10-09 10:35:28"},{"id":"336","title":"[+LUDUS-mouse-move]:","description":"POS:(855;129;0)","date":"2025-10-09 10:35:28"},{"id":"337","title":"[+LUDUS-mouse-move]:","description":"POS:(864;129;0)","date":"2025-10-09 10:35:28"},{"id":"338","title":"[+LUDUS-mouse-move]:","description":"POS:(872;129;0)","date":"2025-10-09 10:35:28"},{"id":"339","title":"[+LUDUS-mouse-move]:","description":"POS:(881;129;0)","date":"2025-10-09 10:35:28"},{"id":"340","title":"[+LUDUS-mouse-move]:","description":"POS:(889;129;0)","date":"2025-10-09 10:35:28"},{"id":"341","title":"[+LUDUS-mouse-move]:","description":"POS:(894;129;0)","date":"2025-10-09 10:35:28"},{"id":"342","title":"[+LUDUS-mouse-move]:","description":"POS:(899;129;0)","date":"2025-10-09 10:35:28"},{"id":"343","title":"[+LUDUS-mouse-move]:","description":"POS:(902;129;0)","date":"2025-10-09 10:35:28"},{"id":"344","title":"[+LUDUS-mouse-move]:","description":"POS:(904;129;0)","date":"2025-10-09 10:35:28"},{"id":"345","title":"[+LUDUS-mouse-move]:","description":"POS:(908;129;0)","date":"2025-10-09 10:35:28"},{"id":"346","title":"[+LUDUS-mouse-move]:","description":"POS:(909;129;0)","date":"2025-10-09 10:35:28"},{"id":"347","title":"[+LUDUS-mouse-move]:","description":"POS:(910;129;0)","date":"2025-10-09 10:35:28"},{"id":"348","title":"[+LUDUS-mouse-move]:","description":"POS:(913;129;0)","date":"2025-10-09 10:35:28"},{"id":"349","title":"[+LUDUS-mouse-move]:","description":"POS:(916;129;0)","date":"2025-10-09 10:35:28"},{"id":"350","title":"[+LUDUS-mouse-move]:","description":"POS:(921;129;0)","date":"2025-10-09 10:35:28"},{"id":"351","title":"[+LUDUS-drag]:","description":"PainelSombra Frame 2 (4) (UnityEngine.Sprite)","date":"2025-10-09 10:35:28"},{"id":"352","title":"[+LUDUS-mouse-move]:","description":"POS:(925;130;0)","date":"2025-10-09 10:35:28"},{"id":"353","title":"[+LUDUS-drag]:","description":"PainelSombra Frame 2 (4) (UnityEngine.Sprite)","date":"2025-10-09 10:35:28"},{"id":"354","title":"[+LUDUS-mouse-move]:","description":"POS:(928;130;0)","date":"2025-10-09 10:35:28"},{"id":"355","title":"[+LUDUS-drag]:","description":"PainelSombra Frame 2 (4) (UnityEngine.Sprite)","date":"2025-10-09 10:35:28"},{"id":"356","title":"[+LUDUS-mouse-move]:","description":"POS:(931;130;0)","date":"2025-10-09 10:35:28"},{"id":"357","title":"[+LUDUS-drag]:","description":"PainelSombra Frame 2 (4) (UnityEngine.Sprite)","date":"2025-10-09 10:35:28"},{"id":"358","title":"[+LUDUS-mouse-click]:","description":"Botão esquerdo .PainelSombra","date":"2025-10-09 10:35:28"},{"id":"359","title":"[+LUDUS-drop]:","description":"PainelSombra Frame 2 (4) (UnityEngine.Sprite)","date":"2025-10-09 10:35:28"},{"id":"360","title":"[+LUDUS-mouse-move]:","description":"POS:(932;130;0)","date":"2025-10-09 10:35:28"},{"id":"361","title":"[+LUDUS-mouse-move]:","description":"POS:(933;130;0)","date":"2025-10-09 10:35:28"},{"id":"362","title":"[+LUDUS-mouse-move]:","description":"POS:(931;131;0)","date":"2025-10-09 10:35:28"},{"id":"363","title":"[+LUDUS-mouse-move]:","description":"POS:(924;131;0)","date":"2025-10-09 10:35:28"},{"id":"364","title":"[+LUDUS-mouse-move]:","description":"POS:(914;131;0)","date":"2025-10-09 10:35:28"},{"id":"365","title":"[+LUDUS-drag]:","description":"PainelSombra Frame 2 (4) (UnityEngine.Sprite)","date":"2025-10-09 10:35:28"},{"id":"366","title":"[+LUDUS-mouse-move]:","description":"POS:(896;131;0)","date":"2025-10-09 10:35:28"},{"id":"367","title":"[+LUDUS-drag]:","description":"PainelSombra Frame 2 (4) (UnityEngine.Sprite)","date":"2025-10-09 10:35:28"},{"id":"368","title":"[+LUDUS-mouse-move]:","description":"POS:(875;134;0)","date":"2025-10-09 10:35:28"},{"id":"369","title":"[+LUDUS-drag]:","description":"PainelSombra Frame 2 (4) (UnityEngine.Sprite)","date":"2025-10-09 10:35:28"},{"id":"370","title":"[+LUDUS-mouse-move]:","description":"POS:(848;134;0)","date":"2025-10-09 10:35:28"},{"id":"371","title":"[+LUDUS-drag]:","description":"PainelSombra Frame 2 (4) (UnityEngine.Sprite)","date":"2025-10-09 10:35:28"},{"id":"372","title":"[+LUDUS-mouse-move]:","description":"POS:(817;137;0)","date":"2025-10-09 10:35:28"},{"id":"373","title":"[+LUDUS-drag]:","description":"PainelSombra Frame 2 (4) (UnityEngine.Sprite)","date":"2025-10-09 10:35:28"},{"id":"374","title":"[+LUDUS-mouse-click]:","description":"Botão esquerdo .PainelSombra","date":"2025-10-09 10:35:28"},{"id":"375","title":"[+LUDUS-drop]:","description":"PainelSombra Frame 2 (4) (UnityEngine.Sprite)","date":"2025-10-09 10:35:28"},{"id":"376","title":"[+LUDUS-mouse-move]:","description":"POS:(749;147;0)","date":"2025-10-09 10:35:28"},{"id":"377","title":"[+LUDUS-mouse-move]:","description":"POS:(712;152;0)","date":"2025-10-09 10:35:28"},{"id":"378","title":"[+LUDUS-mouse-move]:","description":"POS:(683;157;0)","date":"2025-10-09 10:35:28"},{"id":"379","title":"[+LUDUS-mouse-move]:","description":"POS:(656;157;0)","date":"2025-10-09 10:35:28"},{"id":"380","title":"[+LUDUS-mouse-move]:","description":"POS:(634;157;0)","date":"2025-10-09 10:35:28"},{"id":"381","title":"[+LUDUS-mouse-move]:","description":"POS:(617;157;0)","date":"2025-10-09 10:35:28"},{"id":"382","title":"[+LUDUS-mouse-move]:","description":"POS:(596;157;0)","date":"2025-10-09 10:35:28"},{"id":"383","title":"[+LUDUS-mouse-move]:","description":"POS:(590;154;0)","date":"2025-10-09 10:35:28"},{"id":"384","title":"[+LUDUS-mouse-move]:","description":"POS:(587;154;0)","date":"2025-10-09 10:35:28"},{"id":"385","title":"[+LUDUS-mouse-move]:","description":"POS:(584;153;0)","date":"2025-10-09 10:35:28"},{"id":"386","title":"[+LUDUS-mouse-move]:","description":"POS:(581;152;0)","date":"2025-10-09 10:35:28"},{"id":"387","title":"[+LUDUS-mouse-move]:","description":"POS:(580;151;0)","date":"2025-10-09 10:35:28"},{"id":"388","title":"[+LUDUS-mouse-move]:","description":"POS:(579;151;0)","date":"2025-10-09 10:35:28"},{"id":"389","title":"[+LUDUS-mouse-move]:","description":"POS:(576;151;0)","date":"2025-10-09 10:35:28"},{"id":"390","title":"[+LUDUS-mouse-move]:","description":"POS:(574;151;0)","date":"2025-10-09 10:35:28"},{"id":"391","title":"[+LUDUS-mouse-move]:","description":"POS:(570;150;0)","date":"2025-10-09 10:35:28"},{"id":"392","title":"[+LUDUS-drag]:","description":"sombra(Clone)(Clone) sombra_0 (UnityEngine.Sprite)","date":"2025-10-09 10:35:28"},{"id":"393","title":"[+LUDUS-mouse-move]:","description":"POS:(568;150;0)","date":"2025-10-09 10:35:28"},{"id":"394","title":"[+LUDUS-drag]:","description":"sombra(Clone)(Clone) sombra_0 (UnityEngine.Sprite)","date":"2025-10-09 10:35:28"},{"id":"395","title":"[+LUDUS-mouse-move]:","description":"POS:(563;150;0)","date":"2025-10-09 10:35:28"},{"id":"396","title":"[+LUDUS-drag]:","description":"sombra(Clone)(Clone) sombra_0 (UnityEngine.Sprite)","date":"2025-10-09 10:35:28"},{"id":"397","title":"[+LUDUS-mouse-click]:","description":"Botão esquerdo .sombra(Clone)(Clone)","date":"2025-10-09 10:35:28"},{"id":"398","title":"[+LUDUS-drop]:","description":"sombra(Clone)(Clone) sombra_0 (UnityEngine.Sprite)","date":"2025-10-09 10:35:28"},{"id":"399","title":"[+LUDUS-mouse-move]:","description":"POS:(558;150;0)","date":"2025-10-09 10:35:28"},{"id":"400","title":"[+LUDUS-mouse-move]:","description":"POS:(544;150;0)","date":"2025-10-09 10:35:28"},{"id":"401","title":"[+LUDUS-mouse-move]:","description":"POS:(536;150;0)","date":"2025-10-09 10:35:28"},{"id":"402","title":"[+LUDUS-mouse-move]:","description":"POS:(531;150;0)","date":"2025-10-09 10:35:28"},{"id":"403","title":"[+LUDUS-mouse-move]:","description":"POS:(525;150;0)","date":"2025-10-09 10:35:28"},{"id":"404","title":"[+LUDUS-mouse-move]:","description":"POS:(524;150;0)","date":"2025-10-09 10:35:28"},{"id":"405","title":"[+LUDUS-mouse-move]:","description":"POS:(523;149;0)","date":"2025-10-09 10:35:28"},{"id":"406","title":"[+LUDUS-mouse-move]:","description":"POS:(522;149;0)","date":"2025-10-09 10:35:28"},{"id":"407","title":"[+LUDUS-mouse-click]:","description":"Botão esquerdo .PainelSombra","date":"2025-10-09 10:35:28"},{"id":"408","title":"[+LUDUS-mouse-move]:","description":"POS:(517;149;0)","date":"2025-10-09 10:35:28"},{"id":"409","title":"[+LUDUS-mouse-move]:","description":"POS:(511;155;0)","date":"2025-10-09 10:35:28"},{"id":"410","title":"[+LUDUS-mouse-move]:","description":"POS:(500;164;0)","date":"2025-10-09 10:35:28"},{"id":"411","title":"[+LUDUS-mouse-move]:","description":"POS:(485;176;0)","date":"2025-10-09 10:35:28"},{"id":"412","title":"[+LUDUS-mouse-move]:","description":"POS:(468;191;0)","date":"2025-10-09 10:35:28"},{"id":"413","title":"[+LUDUS-mouse-move]:","description":"POS:(456;200;0)","date":"2025-10-09 10:35:28"},{"id":"414","title":"[+LUDUS-mouse-move]:","description":"POS:(446;208;0)","date":"2025-10-09 10:35:28"},{"id":"415","title":"[+LUDUS-mouse-move]:","description":"POS:(439;215;0)","date":"2025-10-09 10:35:28"},{"id":"416","title":"[+LUDUS-mouse-move]:","description":"POS:(437;219;0)","date":"2025-10-09 10:35:28"},{"id":"417","title":"[+LUDUS-mouse-move]:","description":"POS:(436;219;0)","date":"2025-10-09 10:35:28"},{"id":"418","title":"[+LUDUS-mouse-move]:","description":"POS:(436;220;0)","date":"2025-10-09 10:35:28"},{"id":"419","title":"[+LUDUS-mouse-move]:","description":"POS:(436;221;0)","date":"2025-10-09 10:35:28"},{"id":"420","title":"[+LUDUS-mouse-move]:","description":"POS:(437;221;0)","date":"2025-10-09 10:35:28"},{"id":"421","title":"[+LUDUS-mouse-move]:","description":"POS:(440;221;0)","date":"2025-10-09 10:35:28"},{"id":"422","title":"[+LUDUS-mouse-move]:","description":"POS:(443;221;0)","date":"2025-10-09 10:35:28"},{"id":"423","title":"[+LUDUS-mouse-move]:","description":"POS:(450;221;0)","date":"2025-10-09 10:35:28"},{"id":"424","title":"[+LUDUS-mouse-move]:","description":"POS:(462;215;0)","date":"2025-10-09 10:35:28"},{"id":"425","title":"[+LUDUS-mouse-move]:","description":"POS:(480;204;0)","date":"2025-10-09 10:35:28"},{"id":"426","title":"[+LUDUS-mouse-move]:","description":"POS:(517;186;0)","date":"2025-10-09 10:35:29"},{"id":"427","title":"[+LUDUS-mouse-move]:","description":"POS:(553;172;0)","date":"2025-10-09 10:35:29"},{"id":"428","title":"[+LUDUS-mouse-move]:","description":"POS:(600;152;0)","date":"2025-10-09 10:35:29"},{"id":"429","title":"[+LUDUS-mouse-move]:","description":"POS:(638;141;0)","date":"2025-10-09 10:35:29"},{"id":"430","title":"[+LUDUS-mouse-move]:","description":"POS:(687;130;0)","date":"2025-10-09 10:35:29"},{"id":"431","title":"[+LUDUS-mouse-move]:","description":"POS:(732;118;0)","date":"2025-10-09 10:35:29"},{"id":"432","title":"[+LUDUS-mouse-move]:","description":"POS:(773;107;0)","date":"2025-10-09 10:35:29"},{"id":"433","title":"[+LUDUS-mouse-move]:","description":"POS:(806;97;0)","date":"2025-10-09 10:35:29"},{"id":"434","title":"[+LUDUS-mouse-move]:","description":"POS:(832;90;0)","date":"2025-10-09 10:35:29"},{"id":"435","title":"[+LUDUS-mouse-move]:","description":"POS:(855;83;0)","date":"2025-10-09 10:35:29"},{"id":"436","title":"[+LUDUS-mouse-move]:","description":"POS:(871;79;0)","date":"2025-10-09 10:35:29"},{"id":"437","title":"[+LUDUS-mouse-move]:","description":"POS:(892;75;0)","date":"2025-10-09 10:35:29"},{"id":"438","title":"[+LUDUS-mouse-move]:","description":"POS:(898;75;0)","date":"2025-10-09 10:35:29"},{"id":"439","title":"[+LUDUS-mouse-move]:","description":"POS:(906;75;0)","date":"2025-10-09 10:35:29"},{"id":"440","title":"[+LUDUS-mouse-move]:","description":"POS:(909;73;0)","date":"2025-10-09 10:35:29"},{"id":"441","title":"[+LUDUS-mouse-move]:","description":"POS:(912;73;0)","date":"2025-10-09 10:35:29"},{"id":"442","title":"[+LUDUS-mouse-move]:","description":"POS:(913;73;0)","date":"2025-10-09 10:35:29"},{"id":"443","title":"[+LUDUS-mouse-move]:","description":"POS:(915;73;0)","date":"2025-10-09 10:35:29"},{"id":"444","title":"[+LUDUS-mouse-move]:","description":"POS:(918;73;0)","date":"2025-10-09 10:35:29"},{"id":"445","title":"[+LUDUS-mouse-move]:","description":"POS:(919;73;0)","date":"2025-10-09 10:35:29"},{"id":"446","title":"[+LUDUS-mouse-move]:","description":"POS:(922;73;0)","date":"2025-10-09 10:35:29"},{"id":"447","title":"[+LUDUS-mouse-move]:","description":"POS:(923;73;0)","date":"2025-10-09 10:35:29"},{"id":"448","title":"[+LUDUS-mouse-move]:","description":"POS:(924;73;0)","date":"2025-10-09 10:35:29"},{"id":"449","title":"[+LUDUS-mouse-move]:","description":"POS:(927;75;0)","date":"2025-10-09 10:35:29"},{"id":"450","title":"[+LUDUS-mouse-move]:","description":"POS:(930;76;0)","date":"2025-10-09 10:35:29"},{"id":"451","title":"[+LUDUS-mouse-move]:","description":"POS:(931;77;0)","date":"2025-10-09 10:35:29"},{"id":"452","title":"[+LUDUS-mouse-move]:","description":"POS:(931;78;0)","date":"2025-10-09 10:35:29"},{"id":"453","title":"[+LUDUS-mouse-move]:","description":"POS:(933;79;0)","date":"2025-10-09 10:35:29"},{"id":"454","title":"[+LUDUS-mouse-move]:","description":"POS:(934;81;0)","date":"2025-10-09 10:35:29"},{"id":"455","title":"[+LUDUS-mouse-move]:","description":"POS:(936;82;0)","date":"2025-10-09 10:35:29"},{"id":"456","title":"[+LUDUS-mouse-move]:","description":"POS:(936;83;0)","date":"2025-10-09 10:35:29"},{"id":"457","title":"[+LUDUS-mouse-click]:","description":"Botão esquerdo .btnProximo","date":"2025-10-09 10:35:29"}]}
